quizapi/__init__.py
quizapi-0.1.0.dist-info/METADATA
quizapi-0.1.0.dist-info/WHEEL
quizapi-0.1.0.dist-info/top_level.txt
quizapi-0.1.0.dist-info/RECORD
